azure/mgmt/containerregistry/__init__.py
azure/mgmt/containerregistry/_configuration.py
azure/mgmt/containerregistry/_container_registry_management_client.py
azure/mgmt/containerregistry/_serialization.py
azure/mgmt/containerregistry/_version.py
azure/mgmt/containerregistry/models.py
azure/mgmt/containerregistry/py.typed
azure/mgmt/containerregistry/aio/__init__.py
azure/mgmt/containerregistry/aio/_configuration.py
azure/mgmt/containerregistry/aio/_container_registry_management_client.py
azure/mgmt/containerregistry/v2019_05_01/__init__.py
azure/mgmt/containerregistry/v2019_05_01/_configuration.py
azure/mgmt/containerregistry/v2019_05_01/_container_registry_management_client.py
azure/mgmt/containerregistry/v2019_05_01/_patch.py
azure/mgmt/containerregistry/v2019_05_01/_version.py
azure/mgmt/containerregistry/v2019_05_01/py.typed
azure/mgmt/containerregistry/v2019_05_01/aio/__init__.py
azure/mgmt/containerregistry/v2019_05_01/aio/_configuration.py
azure/mgmt/containerregistry/v2019_05_01/aio/_container_registry_management_client.py
azure/mgmt/containerregistry/v2019_05_01/aio/_patch.py
azure/mgmt/containerregistry/v2019_05_01/aio/operations/__init__.py
azure/mgmt/containerregistry/v2019_05_01/aio/operations/_operations.py
azure/mgmt/containerregistry/v2019_05_01/aio/operations/_patch.py
azure/mgmt/containerregistry/v2019_05_01/aio/operations/_registries_operations.py
azure/mgmt/containerregistry/v2019_05_01/aio/operations/_replications_operations.py
azure/mgmt/containerregistry/v2019_05_01/aio/operations/_webhooks_operations.py
azure/mgmt/containerregistry/v2019_05_01/models/__init__.py
azure/mgmt/containerregistry/v2019_05_01/models/_container_registry_management_client_enums.py
azure/mgmt/containerregistry/v2019_05_01/models/_models_py3.py
azure/mgmt/containerregistry/v2019_05_01/models/_patch.py
azure/mgmt/containerregistry/v2019_05_01/operations/__init__.py
azure/mgmt/containerregistry/v2019_05_01/operations/_operations.py
azure_mgmt_containerregistry-12.0.0.dist-info/LICENSE
azure_mgmt_containerregistry-12.0.0.dist-info/METADATA
azure_mgmt_containerregistry-12.0.0.dist-info/WHEEL
azure_mgmt_containerregistry-12.0.0.dist-info/top_level.txt
azure_mgmt_containerregistry-12.0.0.dist-info/RECORD
